[
{"url": "https://www.chordtela.com/2022/04/near-mantan.html"},
{"url": "https://www.chordtela.com/2022/04/near-hilang.html"},
{"url": "https://www.chordtela.com/2022/04/jay-you.html"},
{"url": "https://www.chordtela.com/2022/04/fanita-teumika.html"},
{"url": "https://www.chordtela.com/2022/04/jay-goodbye.html"},
{"url": "https://www.chordtela.com/2022/04/kintani-cangguang.html"},
{"url": "https://www.chordtela.com/2022/04/jay-trimakasih.html"},
{"url": "https://www.chordtela.com/2022/04/ngatmombilung-tolooong.html"},
{"url": "https://www.chordtela.com/2022/04/deamn-summer-love.html"},
{"url": "https://www.chordtela.com/2022/04/laoneis-hanya-simpananmu.html"},
{"url": "https://www.chordtela.com/2022/04/jihan-audy-lepaskanlah.html"},
{"url": "https://www.chordtela.com/2022/04/the-rain-menepi.html"},
{"url": "https://www.chordtela.com/2022/04/artdiaz-kisah-kita.html"},
{"url": "https://www.chordtela.com/2022/04/pendhoza-ngene-banget.html"},
{"url": "https://www.chordtela.com/2022/04/aprilian-lelah-berjuang.html"},
{"url": "https://www.chordtela.com/2022/04/the-chainsmokers-riptide.html"},
{"url": "https://www.chordtela.com/2022/04/justin-bieber-ghost.html"},
{"url": "https://www.chordtela.com/2022/04/conan-gray-memories.html"},
{"url": "https://www.chordtela.com/2022/04/silva-hayati-terjatuh.html"},
{"url": "https://www.chordtela.com/2022/04/anitta-love-you.html"},
{"url": "https://www.chordtela.com/2022/04/safira-inema-lepaskanlah.html"},
{"url": "https://www.chordtela.com/2022/04/mkartikawati-bilang-sayang.html"},
{"url": "https://www.chordtela.com/2022/04/wizz-baker-bersamamu.html"},
{"url": "https://www.chordtela.com/2022/04/faouzia-rip-love.html"},
{"url": "https://www.chordtela.com/2022/04/mkartikawati-bukan-sa.html"},
{"url": "https://www.chordtela.com/2022/04/fauzana-ratok-palupuah.html"},
{"url": "https://www.chordtela.com/2022/04/the-warning-money.html"},
{"url": "https://www.chordtela.com/2022/04/todrick-hall-queen.html"},
{"url": "https://www.chordtela.com/2022/04/febian-tentang-kita.html"},
{"url": "https://www.chordtela.com/2022/04/candria-yang-kumau.html"},
{"url": "https://www.chordtela.com/2022/04/ressa-adzando-jodoh.html"},
{"url": "https://www.chordtela.com/2022/04/boby-berliandika-mawar.html"},
{"url": "https://www.chordtela.com/2022/04/tekomlaku-bedo-karepe.html"},
{"url": "https://www.chordtela.com/2022/04/vicky-salamor-stop.html"},
{"url": "https://www.chordtela.com/2022/04/dina-rubby-pembohong.html"},
{"url": "https://www.chordtela.com/2022/04/obbie-messakh-shelly.html"},
{"url": "https://www.chordtela.com/2022/04/rachmat-kartolo-henny.html"},
{"url": "https://www.chordtela.com/2022/04/els-warouw-tuhan.html"},
{"url": "https://www.chordtela.com/2022/04/mkartikawati-happy-birthday.html"},
{"url": "https://www.chordtela.com/2022/04/one-path-hasbunallah.html"},
{"url": "https://www.chordtela.com/2022/04/mahalini-kisah-sempurna.html"},
{"url": "https://www.chordtela.com/2022/04/muni-long-another.html"},
{"url": "https://www.chordtela.com/2022/04/yelse-cinta-terlerai.html"},
{"url": "https://www.chordtela.com/2022/04/mkartikawati-miss-you.html"},
{"url": "https://www.chordtela.com/2022/04/mkartikawati-di-pelaminan.html"},
{"url": "https://www.chordtela.com/2022/04/dwisan-drama-korea.html"},
{"url": "https://www.chordtela.com/2022/04/mkartikawati-su-berjuang.html"},
{"url": "https://www.chordtela.com/2022/04/lila-safira-lawas.html"},
{"url": "https://www.chordtela.com/2022/04/tika-pagraky-sayang.html"},
{"url": "https://www.chordtela.com/2022/04/bayu-wibowo-ngimpi.html"},
{"url": "https://www.chordtela.com/2022/04/wizz-baker-tarada.html"},
{"url": "https://www.chordtela.com/2022/04/mkartikawati-cuma-tanya.html"},
{"url": "https://www.chordtela.com/2022/04/juicy-luicy-tampar.html"},
{"url": "https://www.chordtela.com/2022/04/vagetoz-lupa-bersyukur.html"},
{"url": "https://www.chordtela.com/2022/04/near-mkartikawati-pertama.html"},
{"url": "https://www.chordtela.com/2022/04/elegy-pagi-terurai.html"},
{"url": "https://www.chordtela.com/2022/04/dj-qhelfin-amelia.html"},
{"url": "https://www.chordtela.com/2022/04/vance-joy-clarity.html"},
{"url": "https://www.chordtela.com/2022/04/budi-arsa-langgeng.html"},
{"url": "https://www.chordtela.com/2022/04/mkartikawati-rindu-bangsat.html"},
{"url": "https://www.chordtela.com/2022/04/yelse-kepalsuan-cinta.html"},
{"url": "https://www.chordtela.com/2022/04/maulandafa-mohon-ampunan.html"},
{"url": "https://www.chordtela.com/2022/04/ria-angelina-senyum.html"},
{"url": "https://www.chordtela.com/2022/04/aswin-win-tiktok.html"},
{"url": "https://www.chordtela.com/2022/04/aprilian-cinta-hilang.html"},
{"url": "https://www.chordtela.com/2022/04/alec-benjamin-speakers.html"},
{"url": "https://www.chordtela.com/2022/04/faradilla-tak-ngalah.html"},
{"url": "https://www.chordtela.com/2022/04/mkartikawati-rindu-mama.html"},
{"url": "https://www.chordtela.com/2022/04/andrikoga-taragak-pulang.html"},
{"url": "https://www.chordtela.com/2022/04/sabyan-ana-ana.html"},
{"url": "https://www.chordtela.com/2022/04/dadido-sholawatan-yuk.html"},
{"url": "https://www.chordtela.com/2022/04/near-kembali-mkartikawati.html"},
{"url": "https://www.chordtela.com/2022/04/ammy-cleo-yakinlah.html"},
{"url": "https://www.chordtela.com/2022/04/bergek-gadis-impian.html"},
{"url": "https://www.chordtela.com/2022/04/elizabeth-sudira-pesona.html"},
{"url": "https://www.chordtela.com/2022/04/wahyu-os-dinda.html"},
{"url": "https://www.chordtela.com/2022/04/vita-alvia-untukmu.html"},
{"url": "https://www.chordtela.com/2022/04/ria-angelina-senandungku.html"},
{"url": "https://www.chordtela.com/2022/04/ipank-jaso-tanah.html"},
{"url": "https://www.chordtela.com/2022/04/dul-jaelani-astaghfirullah.html"},
{"url": "https://www.chordtela.com/2022/04/lyn-lapid-off-day.html"},
{"url": "https://www.chordtela.com/2022/04/alec-benjamin-dopamine-addict.html"},
{"url": "https://www.chordtela.com/2022/04/ratu-aulia-siapa-jodohku.html"},
{"url": "https://www.chordtela.com/2022/04/three-days-grace-lifetime.html"},
{"url": "https://www.chordtela.com/2022/04/angel-merem-plahoroning-ati.html"},
{"url": "https://www.chordtela.com/2022/04/yelse-ku-dilanda-cinta.html"},
{"url": "https://www.chordtela.com/2022/04/anitta-versions-of-me.html"},
{"url": "https://www.chordtela.com/2022/04/angel-merem-timbang-kejeron.html"},
{"url": "https://www.chordtela.com/2022/04/the-rain-mendengar-kabar.html"},
{"url": "https://www.chordtela.com/2022/04/fani-bhayangkara-kadung-getun.html"},
{"url": "https://www.chordtela.com/2022/04/jhon-kinawa-baru-kusedari.html"},
{"url": "https://www.chordtela.com/2022/04/widi-widiana-aran-orin.html"},
{"url": "https://www.chordtela.com/2022/04/widi-widiana-jaman-kaliyuga.html"},
{"url": "https://www.chordtela.com/2022/04/maher-zain-rahmatun-lilalameen.html"},
{"url": "https://www.chordtela.com/2022/04/clara-herison-sempurna-denganmu.html"},
{"url": "https://www.chordtela.com/2022/04/qveen-herby-f-myself.html"},
{"url": "https://www.chordtela.com/2022/04/tiara-andini-janji-setia.html"},
{"url": "https://www.chordtela.com/2022/04/tegar-septian-setahun-berlalu.html"},
{"url": "https://www.chordtela.com/2022/04/whllyano-tetap-hanya-ko.html"},
{"url": "https://www.chordtela.com/2022/04/bagus-wirata-pejalan-tresna.html"},
{"url": "https://www.chordtela.com/2022/04/nurul-munira-dimana-hatimu.html"},
{"url": "https://www.chordtela.com/2022/04/sunu-matta-rindu-rasul.html"},
{"url": "https://www.chordtela.com/2022/04/elsa-pitaloka-tersiksa-karnamu.html"},
{"url": "https://www.chordtela.com/2022/04/heidy-diana-kusayang-padamu.html"},
{"url": "https://www.chordtela.com/2022/04/yudi-kresna-sing-sanggup.html"},
{"url": "https://www.chordtela.com/2022/04/denis-farasya-penawar-atiku.html"},
{"url": "https://www.chordtela.com/2022/04/pedih-ropi-hitam-manis.html"},
{"url": "https://www.chordtela.com/2022/04/sammy-simorangkir-kisah-abadi.html"},
{"url": "https://www.chordtela.com/2022/04/nindy-ellesse-kau-bersandiwara.html"},
{"url": "https://www.chordtela.com/2022/04/jeffry-lawerance-takat-pengidup.html"},
{"url": "https://www.chordtela.com/2022/04/arief-bertaruh-dalam-cinta.html"},
{"url": "https://www.chordtela.com/2022/04/lydia-natalia-erosi-cinta.html"},
{"url": "https://www.chordtela.com/2022/04/miqbal-ga-ganti-ayang.html"},
{"url": "https://www.chordtela.com/2022/04/gita-kdi-ampuni-aku.html"},
{"url": "https://www.chordtela.com/2022/04/tamin-manise-korban-sandiwara.html"},
{"url": "https://www.chordtela.com/2022/04/ical-majene-jalan-taubatku.html"},
{"url": "https://www.chordtela.com/2022/04/mkartikawati-near-hati-rindu.html"},
{"url": "https://www.chordtela.com/2022/04/near-x-mkartikawati-nanti.html"},
{"url": "https://www.chordtela.com/2022/04/warren-zeiders-wild-horse.html"},
{"url": "https://www.chordtela.com/2022/04/yoga-vhein-proses-cinta.html"},
{"url": "https://www.chordtela.com/2022/04/ifandra-mambangkik-batang-tarandam.html"},
{"url": "https://www.chordtela.com/2022/04/ilux-id-terimalah-tobatku.html"},
{"url": "https://www.chordtela.com/2022/04/carrie-underwood-crazy-angels.html"},
{"url": "https://www.chordtela.com/2022/04/aprilian-larut-dalam-kecewa.html"},
{"url": "https://www.chordtela.com/2022/04/mario-klau-semata-karenamu.html"},
{"url": "https://www.chordtela.com/2022/04/vanny-vabiola-sahabat-kecilku.html"},
{"url": "https://www.chordtela.com/2022/04/wayan-sumade-percuma-berjuang.html"},
{"url": "https://www.chordtela.com/2022/04/febian-titipkan-setiaku-padanya.html"},
{"url": "https://www.chordtela.com/2022/04/alwiansyah-allah-maha-besar.html"},
{"url": "https://www.chordtela.com/2022/04/trixie-mattel-cmon-loretta.html"},
{"url": "https://www.chordtela.com/2022/04/james-ap-wong-siji.html"},
{"url": "https://www.chordtela.com/2022/04/maulana-wijaya-bukan-pemenang.html"},
{"url": "https://www.chordtela.com/2022/04/yollanda-pilu-terbalut-luka.html"},
{"url": "https://www.chordtela.com/2022/04/vicky-marchel-pengkhianatan-cinta.html"},
{"url": "https://www.chordtela.com/2022/04/anak-kompleks-lelah-menunggu.html"},
{"url": "https://www.chordtela.com/2022/04/strange-fruits-music-hello.html"},
{"url": "https://www.chordtela.com/2022/04/suci-tacik-badai-fitnah.html"},
{"url": "https://www.chordtela.com/2022/04/near-mkartikawati-selamat-malam.html"},
{"url": "https://www.chordtela.com/2022/04/ilux-id-posoan-ambyar.html"},
{"url": "https://www.chordtela.com/2022/04/rheka-restu-tertikam-rindu.html"},
{"url": "https://www.chordtela.com/2022/04/deddy-dores-senandung-rindu.html"},
{"url": "https://www.chordtela.com/2022/04/michele-morrone-another-day.html"},
{"url": "https://www.chordtela.com/2022/04/mkartikawati-natal-di-sini.html"},
{"url": "https://www.chordtela.com/2022/04/justy-aldrin-jang-tanya.html"},
{"url": "https://www.chordtela.com/2022/04/niko-moon-easy-tonight.html"},
{"url": "https://www.chordtela.com/2022/04/dian-piesesha-senandung-untukmu.html"},
{"url": "https://www.chordtela.com/2022/04/thomas-arya-peminat-sejatimu.html"},
{"url": "https://www.chordtela.com/2022/04/elsa-pitaloka-penerang-hidupku.html"},
{"url": "https://www.chordtela.com/2022/04/the-palopos-terlanjur-cinta.html"},
{"url": "https://www.chordtela.com/2022/04/near-lagi-ft-jay.html"},
{"url": "https://www.chordtela.com/2022/04/prapatancandi-magelang-ninggal-kenangan.html"},
{"url": "https://www.chordtela.com/2022/04/aish-hanigel-tak-jodoh.html"},
{"url": "https://www.chordtela.com/2022/04/pepeh-sadboy-spek-bidadari.html"},
{"url": "https://www.chordtela.com/2022/04/near-rumah-ft-jay.html"},
{"url": "https://www.chordtela.com/2022/04/harry-parintang-salahkah-diriku.html"},
{"url": "https://www.chordtela.com/2022/04/arief-setia-berbalas-dusta.html"},
{"url": "https://www.chordtela.com/2022/04/patra-hafizh-dewe-wani.html"},
{"url": "https://www.chordtela.com/2022/04/anggi-chandra-jangan-mengaku.html"},
{"url": "https://www.chordtela.com/2022/04/davina-michelle-no-angel.html"},
{"url": "https://www.chordtela.com/2022/04/yoga-vhein-bersujud-padamu.html"},
{"url": "https://www.chordtela.com/2022/04/hendra-kumbara-piye-kabare.html"},
{"url": "https://www.chordtela.com/2022/04/heidy-diana-nyanyikan-lagi.html"},
{"url": "https://www.chordtela.com/2022/04/richie-ricardo-kau-milikku.html"},
{"url": "https://www.chordtela.com/2022/04/tasya-kirana-yowis-maturnuwun.html"},
{"url": "https://www.chordtela.com/2022/04/ziva-magnolya-peri-cintaku.html"},
{"url": "https://www.chordtela.com/2022/04/rayola-pitunang-dalam-lagu.html"},
{"url": "https://www.chordtela.com/2022/04/ratu-aulia-syair-taubat.html"},
{"url": "https://www.chordtela.com/2022/04/andra-respati-galau-karenamu.html"},
{"url": "https://www.chordtela.com/2022/04/alwalid-mz-rasa-cinta.html"},
{"url": "https://www.chordtela.com/2022/04/dian-piesesha-bawalah-senyummu.html"},
{"url": "https://www.chordtela.com/2022/04/anak-kompleks-sa-menyesal.html"},
{"url": "https://www.chordtela.com/2022/04/tryana-tak-sehaluan-lagi.html"},
{"url": "https://www.chordtela.com/2022/04/angel-merem-tekone-sliramu.html"},
{"url": "https://www.chordtela.com/2022/04/anak-kompleks-sa-ikhlas.html"},
{"url": "https://www.chordtela.com/2022/04/rika-zella-terluka-karnamu.html"},
{"url": "https://www.chordtela.com/2022/04/mkartikawati-tra-bisa-pulang.html"},
{"url": "https://www.chordtela.com/2022/04/fiji-blue-feel-something.html"},
{"url": "https://www.chordtela.com/2022/04/widi-widiana-celeng-guling.html"},
{"url": "https://www.chordtela.com/2022/04/silva-hayati-bareh-bilukuik.html"},
{"url": "https://www.chordtela.com/2022/04/dhimas-tedjo-tresnaku-ambyar.html"},
{"url": "https://www.chordtela.com/2022/04/nella-kharisma-butuh-dibelai.html"},
{"url": "https://www.chordtela.com/2022/04/begundal-lowokwaru-hari-raya.html"},
{"url": "https://www.chordtela.com/2022/04/rahmat-findo-parasaian-badan.html"},
{"url": "https://www.chordtela.com/2022/04/rio-adiwardhana-bila-kau.html"},
{"url": "https://www.chordtela.com/2022/04/stephen-sharer-malibu-barbie.html"},
{"url": "https://www.chordtela.com/2022/04/chintami-atmanagara-sifat-pria.html"},
{"url": "https://www.chordtela.com/2022/04/jay-near-pecah-taon.html"},
{"url": "https://www.chordtela.com/2022/04/radja-malam-1000-bulan.html"},
{"url": "https://www.chordtela.com/2022/04/nalury-ditikam-raso-cinto.html"},
{"url": "https://www.chordtela.com/2022/04/kinur-mung-ban-serepmu.html"},
{"url": "https://www.chordtela.com/2022/04/willy-anggawinata-mimpi-indahku.html"},
{"url": "https://www.chordtela.com/2022/04/ucok-baba-bersyukur-padamu.html"},
{"url": "https://www.chordtela.com/2022/04/demy-yoker-kari-cerito.html"},
{"url": "https://www.chordtela.com/2022/04/mkartikawati-cinta-tra-sampe.html"},
{"url": "https://www.chordtela.com/2022/04/lara-silvy-suwe-ngampet.html"},
{"url": "https://www.chordtela.com/2022/04/richie-ricardo-lagu-kesayangan.html"},
{"url": "https://www.chordtela.com/2022/04/valdy-nyonk-ampunkan-aku.html"},
{"url": "https://www.chordtela.com/2022/04/deddy-dores-senyumlah-sayang.html"},
{"url": "https://www.chordtela.com/2022/04/alok-bastille-run-into-trouble.html"},
{"url": "https://www.chordtela.com/2022/04/jenna-davis-look-whos-back.html"},
{"url": "https://www.chordtela.com/2022/04/harry-styles-as-it-was.html"},
{"url": "https://www.chordtela.com/2022/04/zolita-i-fing-love-you.html"},
{"url": "https://www.chordtela.com/2022/04/the-rain-kita-dan-ketidakmungkinan.html"},
{"url": "https://www.chordtela.com/2022/04/kangen-band-kau-begitu-cepat.html"},
{"url": "https://www.chordtela.com/2022/04/maulana-wijaya-aku-yang-kecewa.html"},
{"url": "https://www.chordtela.com/2022/04/little-big-town-hell-yeah.html"},
{"url": "https://www.chordtela.com/2022/04/vany-thursdila-luka-yang-membekas.html"},
{"url": "https://www.chordtela.com/2022/04/asbak-band-janji-untuk-setia.html"},
{"url": "https://www.chordtela.com/2022/04/iskandar-projector-band-indah-intan.html"},
{"url": "https://www.chordtela.com/2022/04/arvian-dwi-satu-shaf-dibelakangku.html"},
{"url": "https://www.chordtela.com/2022/04/anak-kompleks-sa-orang-biasa.html"},
{"url": "https://www.chordtela.com/2022/04/aish-hanigel-ft-ariffirnando-minimisiu.html"},
{"url": "https://www.chordtela.com/2022/04/gustrian-geno-maafkan-aku-kasih.html"},
{"url": "https://www.chordtela.com/2022/04/rika-zella-tak-usah-berharap.html"},
{"url": "https://www.chordtela.com/2022/04/maulana-wijaya-sesalan-tiada-arti.html"},
{"url": "https://www.chordtela.com/2022/04/bergek-hutang-pok-amai-amai.html"},
{"url": "https://www.chordtela.com/2022/04/alesso-words-feat-zara-larsson.html"},
{"url": "https://www.chordtela.com/2022/04/dj-qhelfin-sa-coba-ikhlas.html"},
{"url": "https://www.chordtela.com/2022/04/vicky-koga-inikah-caramu-mencintaiku.html"},
{"url": "https://www.chordtela.com/2022/04/clara-herison-apa-kabar-mantan.html"},
{"url": "https://www.chordtela.com/2022/04/vany-thursdila-terlambat-kau-sadari.html"},
{"url": "https://www.chordtela.com/2022/04/budi-doremi-ingat-dirimu-lagi.html"},
{"url": "https://www.chordtela.com/2022/04/ariski-bendang-tibarau-malah-kironyo.html"},
{"url": "https://www.chordtela.com/2022/04/sazqia-rayani-mananti-nan-kapulang.html"},
{"url": "https://www.chordtela.com/2022/04/ammy-samawa-aku-tau-diri.html"},
{"url": "https://www.chordtela.com/2022/04/near-x-jay-move-on.html"},
{"url": "https://www.chordtela.com/2022/04/anitta-love-me-love-me.html"},
{"url": "https://www.chordtela.com/2022/04/near-biar-sa-jaga-mkartikawati.html"},
{"url": "https://www.chordtela.com/2022/04/vanny-vabiola-ku-tetap-mencintaimu.html"},
{"url": "https://www.chordtela.com/2022/04/jihan-audy-kuserahkan-seluruh-hidupku.html"},
{"url": "https://www.chordtela.com/2022/04/dj-qhelfin-tra-dapat-restu.html"},
{"url": "https://www.chordtela.com/2022/04/vany-thursdila-buka-pintu-hatimu.html"},
{"url": "https://www.chordtela.com/2022/04/elsa-pitaloka-terhanyut-dalam-rindu.html"},
{"url": "https://www.chordtela.com/2022/04/nazia-marwiana-salah-menaruh-hati.html"},
{"url": "https://www.chordtela.com/2022/04/helen-sparingga-seuntai-puisi-untukmu.html"},
{"url": "https://www.chordtela.com/2022/04/gustrian-geno-hanya-bisa-merelakan.html"},
{"url": "https://www.chordtela.com/2022/04/near-sebatas-teman-ft-mkartikawati.html"},
{"url": "https://www.chordtela.com/2022/04/cut-zuhra-terpisah-oleh-masa.html"},
{"url": "https://www.chordtela.com/2022/04/pinki-prananda-cincin-basagi-limo.html"},
{"url": "https://www.chordtela.com/2022/04/almeyda-nayara-di-lain-waktu.html"},
{"url": "https://www.chordtela.com/2022/04/anak-kompleks-sa-tra-bisa.html"},
{"url": "https://www.chordtela.com/2022/04/sri-fayola-galeh-ndak-laku.html"},
{"url": "https://www.chordtela.com/2022/04/yelse-lelah-sudah-ku-mencintaimu.html"},
{"url": "https://www.chordtela.com/2022/04/budi-doremi-maaf-ku-salah.html"},
{"url": "https://www.chordtela.com/2022/04/mamnun-ft-cimbrut-lembah-manah.html"},
{"url": "https://www.chordtela.com/2022/04/tri-suaka-minta-izin-restu.html"},
{"url": "https://www.chordtela.com/2022/04/davina-michelle-nobody-is-perfect.html"},
{"url": "https://www.chordtela.com/2022/04/mario-klau-bertahan-untuk-pergi.html"},
{"url": "https://www.chordtela.com/2022/04/meriam-bellina-kau-semakin-angkuh.html"},
{"url": "https://www.chordtela.com/2022/04/the-rain-salam-dari-ibumu.html"},
{"url": "https://www.chordtela.com/2022/04/rika-zella-luka-tak-berdarah.html"},
{"url": "https://www.chordtela.com/2022/04/zikra-iklaskanku-dengan-yang-lain.html"},
{"url": "https://www.chordtela.com/2022/04/vanny-vabiola-aku-sangat-mencintaimu.html"},
{"url": "https://www.chordtela.com/2022/04/puspa-indah-berharap-kau-kembali.html"},
{"url": "https://www.chordtela.com/2022/04/juliette-dewa-19-feat-ello.html"},
{"url": "https://www.chordtela.com/2022/04/sasya-arkhisna-kesandung-dalan-roto.html"},
{"url": "https://www.chordtela.com/2022/04/syahriyadi-dua-hati-satu-tujuan.html"},
{"url": "https://www.chordtela.com/2022/04/ndarboy-genk-koyo-jogja-istimewa.html"},
{"url": "https://www.chordtela.com/2022/04/intan-selvi-rundiang-pamisah-cinto.html"},
{"url": "https://www.chordtela.com/2022/04/ria-amelia-cinto-jan-dibali.html"},
{"url": "https://www.chordtela.com/2022/04/rheka-restu-janji-yang-terlupakan.html"},
{"url": "https://www.chordtela.com/2022/04/vany-thursdila-cinta-dalam-ilusi.html"},
{"url": "https://www.chordtela.com/2022/04/fibri-novita-aku-bukan-aisyah.html"},
{"url": "https://www.chordtela.com/2022/04/acha-clarissa-rayuan-semanis-madu.html"},
{"url": "https://www.chordtela.com/2022/04/xxditto-tulisan-dalam-kerta-putih.html"},
{"url": "https://www.chordtela.com/2022/04/lara-silvy-semilir-angin-wengi.html"},
{"url": "https://www.chordtela.com/2022/04/wizz-baker-mulai-malam-ini.html"},
{"url": "https://www.chordtela.com/2022/04/fani-ellen-jangan-pergi-cintaku.html"},
{"url": "https://www.chordtela.com/2022/04/fourtwnty-mangu-ft-charita-utami.html"},
{"url": "https://www.chordtela.com/2022/04/teguh-permana-marhaban-ya-ramadhan.html"},
{"url": "https://www.chordtela.com/2022/04/rudi-awan-akan-ku-buktikan.html"},
{"url": "https://www.chordtela.com/2022/04/boby-berliandika-izinkan-hamba-bertaubat.html"},
{"url": "https://www.chordtela.com/2022/04/mcp-sysilia-so-dapa-restu.html"},
{"url": "https://www.chordtela.com/2022/04/syahiba-saufa-joko-tingkir-ngombe-dawet.html"},
{"url": "https://www.chordtela.com/2022/04/silva-hayati-minyak-maha-karambia-murah.html"},
{"url": "https://www.chordtela.com/2022/04/didik-budi-feat-cindi-cintya-terimakasih.html"},
{"url": "https://www.chordtela.com/2022/04/ariski-bendang-hari-pembalasan-itu-nyata.html"},
{"url": "https://www.chordtela.com/2022/04/aprillia-feat-wahyu-mtd-dudu-jodone.html"},
{"url": "https://www.chordtela.com/2022/04/andra-respati-tangis-di-hari-perkawinan.html"},
{"url": "https://www.chordtela.com/2022/04/aprilian-feat-fany-zee-terlanjur-kecewa.html"},
{"url": "https://www.chordtela.com/2022/04/andre-mastijan-biarlah-aku-yang-mengalah.html"},
{"url": "https://www.chordtela.com/2022/04/abah-lala-ojo-dibandingke-feat-iyana.html"},
{"url": "https://www.chordtela.com/2022/04/sarpan-paumbunan-mey-christine-masannang-undinna.html"},
{"url": "https://www.chordtela.com/2022/04/qeiskya-fahira-ft-devino-anggan-datang.html"},
{"url": "https://www.chordtela.com/2022/04/near-di-batas-kota-feat-jay.html"},
{"url": "https://www.chordtela.com/2022/04/yans-boyame-psk-pianak-sing-kerungu.html"},
{"url": "https://www.chordtela.com/2022/04/of-monsters-and-men-this-happiness.html"},
{"url": "https://www.chordtela.com/2022/04/atta-aurel-ft-siti-nurhaliza-alhamdulillah.html"},
{"url": "https://www.chordtela.com/2022/04/lydia-natalia-ku-ingin-kau-mengerti.html"},
{"url": "https://www.chordtela.com/2022/04/kangen-band-cinta-sampai-mati-2.html"},
{"url": "https://www.chordtela.com/2022/04/airin-azhari-kau-akhiri-demi-dia.html"},
{"url": "https://www.chordtela.com/2022/04/sasya-arkhisna-tak-lali-lali-salahmu.html"},
{"url": "https://www.chordtela.com/2022/04/pendamping-didik-budi-feat-cindi-cintya.html"},
{"url": "https://www.chordtela.com/2022/04/arif-lida-duri-kau-tancap-luka.html"},
{"url": "https://www.chordtela.com/2022/04/angga-eqino-bagai-si-ranting-kering.html"},
{"url": "https://www.chordtela.com/2022/04/wandra-kelangan-3-feat-ageng-music.html"},
{"url": "https://www.chordtela.com/2022/04/mang-senior-sekuter-made-in-cina.html"},
{"url": "https://www.chordtela.com/2022/04/jacob-lee-break-my-heart-again.html"},
{"url": "https://www.chordtela.com/2022/04/uncle-djink-ft-donilow-ngamuk-ngamuk.html"},
{"url": "https://www.chordtela.com/2022/04/rahmat-findo-venissa-raso-manaruah-suko.html"},
{"url": "https://www.chordtela.com/2022/05/yelse-persinggahan.html"},
{"url": "https://www.chordtela.com/2022/05/mxmtoon-frown.html"},
{"url": "https://www.chordtela.com/2022/05/faouzia-solie.html"},
{"url": "https://www.chordtela.com/2022/05/got7-nanana.html"},
{"url": "https://www.chordtela.com/2022/05/febian-pulanglah.html"},
{"url": "https://www.chordtela.com/2022/05/boraspati-marantau.html"},
{"url": "https://www.chordtela.com/2022/05/papinka-menangis.html"},
{"url": "https://www.chordtela.com/2022/05/ofenbach-4u.html"},
{"url": "https://www.chordtela.com/2022/05/mxmtoon-haze.html"},
{"url": "https://www.chordtela.com/2022/05/belinda-colorblind.html"},
{"url": "https://www.chordtela.com/2022/05/ngatmombilung-kalah.html"},
{"url": "https://www.chordtela.com/2022/05/ikhlas-menyesal.html"},
{"url": "https://www.chordtela.com/2022/05/indah-sari-cuan.html"},
{"url": "https://www.chordtela.com/2022/05/simi-naked-wire.html"},
{"url": "https://www.chordtela.com/2022/05/ghea-marsella-otewe.html"},
{"url": "https://www.chordtela.com/2022/05/ed-sheeran-penguins.html"},
{"url": "https://www.chordtela.com/2022/05/raffa-affar-salting.html"},
{"url": "https://www.chordtela.com/2022/05/dj-qhelfin-buktikan.html"},
{"url": "https://www.chordtela.com/2022/05/miqbal-ga-ge.html"},
{"url": "https://www.chordtela.com/2022/05/papinka-dimana-cintamu.html"},
{"url": "https://www.chordtela.com/2022/05/omcon-sb-yasudah.html"},
{"url": "https://www.chordtela.com/2022/05/livingston-the-author.html"},
{"url": "https://www.chordtela.com/2022/05/damara-de-sesambungan.html"},
{"url": "https://www.chordtela.com/2022/05/wanna-bee-melepaskanmu.html"},
{"url": "https://www.chordtela.com/2022/05/adei-pujaan-hati.html"},
{"url": "https://www.chordtela.com/2022/05/ali-gatie-idk.html"},
{"url": "https://www.chordtela.com/2022/05/faouzia-i-know.html"},
{"url": "https://www.chordtela.com/2022/05/tiko-venture-quest.html"},
{"url": "https://www.chordtela.com/2022/05/becky-g-borracha.html"},
{"url": "https://www.chordtela.com/2022/05/avery-anna-critic.html"},
{"url": "https://www.chordtela.com/2022/05/papinka-menghapus-rasa.html"},
{"url": "https://www.chordtela.com/2022/05/woosung-modern-life.html"},
{"url": "https://www.chordtela.com/2022/05/kailee-morgue-loser.html"},
{"url": "https://www.chordtela.com/2022/05/near-mimpi-indah.html"},
{"url": "https://www.chordtela.com/2022/05/mimi-webb-goodbye.html"},
{"url": "https://www.chordtela.com/2022/05/faouzia-anybody-else.html"},
{"url": "https://www.chordtela.com/2022/05/lyn-lapid-comatose.html"},
{"url": "https://www.chordtela.com/2022/05/yollanda-terlalu-sakit.html"},
{"url": "https://www.chordtela.com/2022/05/lavora-pengen-bali.html"},
{"url": "https://www.chordtela.com/2022/05/armada-penggemar-beratmu.html"},
{"url": "https://www.chordtela.com/2022/05/gamma1-cinta-pertama.html"},
{"url": "https://www.chordtela.com/2022/05/armada-kita-bersaudara.html"},
{"url": "https://www.chordtela.com/2022/05/keweh-astrawan-optimis.html"},
{"url": "https://www.chordtela.com/2022/05/alwalid-mz-tega.html"},
{"url": "https://www.chordtela.com/2022/05/setio-okta-isty.html"},
{"url": "https://www.chordtela.com/2022/05/kerispatih-pernah-terluka.html"},
{"url": "https://www.chordtela.com/2022/05/conan-gray-yours.html"},
{"url": "https://www.chordtela.com/2022/05/yollanda-ada-sayang.html"},
{"url": "https://www.chordtela.com/2022/05/daun-jatuh-bungkam.html"},
{"url": "https://www.chordtela.com/2022/05/woosung-phase-me.html"},
{"url": "https://www.chordtela.com/2022/05/yelse-keabadian-cinta.html"},
{"url": "https://www.chordtela.com/2022/05/ella-mai-trying.html"},
{"url": "https://www.chordtela.com/2022/05/papinka-pencuri-hati.html"},
{"url": "https://www.chordtela.com/2022/05/armada-duduk-bersama.html"},
{"url": "https://www.chordtela.com/2022/05/ona-hetharua-malu.html"},
{"url": "https://www.chordtela.com/2022/05/papinka-keras-hati.html"},
{"url": "https://www.chordtela.com/2022/05/fauzana-mahapuih-jajak.html"},
{"url": "https://www.chordtela.com/2022/05/armada-orang-ketiga.html"},
{"url": "https://www.chordtela.com/2022/05/lyn-lapid-infinite.html"},
{"url": "https://www.chordtela.com/2022/05/v2last-seperti-bintang.html"},
{"url": "https://www.chordtela.com/2022/05/syahril-hanya-mimpi.html"},
{"url": "https://www.chordtela.com/2022/05/elkasih-reborn-rasa.html"},
{"url": "https://www.chordtela.com/2022/05/mega-resinta-semesta.html"},
{"url": "https://www.chordtela.com/2022/05/alwalid-mz-maafkanlah.html"},
{"url": "https://www.chordtela.com/2022/05/kiesha-alvaro-rahasia.html"},
{"url": "https://www.chordtela.com/2022/05/syahriyadi-pamit-kerja.html"},
{"url": "https://www.chordtela.com/2022/05/ilux-id-sakit.html"},
{"url": "https://www.chordtela.com/2022/05/adista-ku-pergi.html"},
{"url": "https://www.chordtela.com/2022/05/brigade-07-bintangku.html"},
{"url": "https://www.chordtela.com/2022/05/baby-shima-pulang.html"},
{"url": "https://www.chordtela.com/2022/05/woosung-come-down.html"},
{"url": "https://www.chordtela.com/2022/05/xxditto-suara-hati.html"},
{"url": "https://www.chordtela.com/2022/05/ratu-pargoy-bestie.html"},
{"url": "https://www.chordtela.com/2022/05/lyn-lapid-itsy-bitsy.html"},
{"url": "https://www.chordtela.com/2022/05/justy-aldrin-masih-sandiri.html"},
{"url": "https://www.chordtela.com/2022/05/dhevy-geranium-putuskan-saja.html"},
{"url": "https://www.chordtela.com/2022/05/sena-pati-nembus-dodo.html"},
{"url": "https://www.chordtela.com/2022/05/ilux-id-kemulan-udan.html"},
{"url": "https://www.chordtela.com/2022/05/wizz-baker-terlalu-mengerti.html"},
{"url": "https://www.chordtela.com/2022/05/shila-amzah-khilaf-asmara.html"},
{"url": "https://www.chordtela.com/2022/05/mahen-mimpi-tentang-dia.html"},
{"url": "https://www.chordtela.com/2022/05/near-hati-ko-silang.html"},
{"url": "https://www.chordtela.com/2022/05/jihan-audy-belah-dadaku.html"},
{"url": "https://www.chordtela.com/2022/05/nabasa-trio-lupa-diri.html"},
{"url": "https://www.chordtela.com/2022/05/gustrian-geno-selamat-tinggal.html"},
{"url": "https://www.chordtela.com/2022/05/wulandary-terdiam-menanggung-luka.html"},
{"url": "https://www.chordtela.com/2022/05/arief-terlalu-kejam-untukku.html"},
{"url": "https://www.chordtela.com/2022/05/paksi-band-keroncong-lebaran.html"},
{"url": "https://www.chordtela.com/2022/05/febian-setiamu-ku-pertanyakan.html"},
{"url": "https://www.chordtela.com/2022/05/francis-karel-holding-on.html"},
{"url": "https://www.chordtela.com/2022/05/tyok-satrio-katakan-padamu.html"},
{"url": "https://www.chordtela.com/2022/05/dyah-novia-ingkar-janji.html"},
{"url": "https://www.chordtela.com/2022/05/eno-viola-tanyakan-hati.html"},
{"url": "https://www.chordtela.com/2022/05/brigade-07-wanita-terkuat.html"},
{"url": "https://www.chordtela.com/2022/05/tiffany-takalok-manihnyo-cinto.html"},
{"url": "https://www.chordtela.com/2022/05/near-nalam-ft-jay.html"},
{"url": "https://www.chordtela.com/2022/05/rizky-febian-ribuan-hati.html"},
{"url": "https://www.chordtela.com/2022/05/papinka-jalani-hidup-sendiri.html"},
{"url": "https://www.chordtela.com/2022/05/the-rain-di-perantauan.html"},
{"url": "https://www.chordtela.com/2022/05/acap-tarabas-disebalik-tawaku.html"},
{"url": "https://www.chordtela.com/2022/05/fibri-novita-kembali-suci.html"},
{"url": "https://www.chordtela.com/2022/05/bagus-wirata-dosa-terindah.html"},
{"url": "https://www.chordtela.com/2022/05/elsa-pitaloka-mendung-kelabu.html"},
{"url": "https://www.chordtela.com/2022/05/putri-sagita-kang-pansos.html"},
{"url": "https://www.chordtela.com/2022/05/woro-widowati-angel-3.html"},
{"url": "https://www.chordtela.com/2022/05/andis-sagara-aku-rindu.html"},
{"url": "https://www.chordtela.com/2022/05/rambun-pamenan-palaminan-mamerah.html"},
{"url": "https://www.chordtela.com/2022/05/marsada-star-bunga-pancur.html"},
{"url": "https://www.chordtela.com/2022/05/rendy-pandugo-pamungkas-friends.html"},
{"url": "https://www.chordtela.com/2022/05/yan-diasa-nyirami-tangis.html"},
{"url": "https://www.chordtela.com/2022/05/alan-walker-the-drum.html"},
{"url": "https://www.chordtela.com/2022/05/andra-respati-siapa-dia.html"},
{"url": "https://www.chordtela.com/2022/05/rindra-putra-nek-akhire.html"},
{"url": "https://www.chordtela.com/2022/05/kezia-aku-masih-memikirkanmu.html"},
{"url": "https://www.chordtela.com/2022/05/near-rindu-ft-jay.html"},
{"url": "https://www.chordtela.com/2022/05/tiara-queen-manunggu-pinangan.html"},
{"url": "https://www.chordtela.com/2022/05/yudi-kresna-percuma-nyayangin.html"},
{"url": "https://www.chordtela.com/2022/05/carlos-insan-tak-berpunya.html"},
{"url": "https://www.chordtela.com/2022/05/the-rain-halaman-berbeda.html"},
{"url": "https://www.chordtela.com/2022/05/refour-of-sins-lost.html"},
{"url": "https://www.chordtela.com/2022/05/sri-fayola-samudera-cinta.html"},
{"url": "https://www.chordtela.com/2022/05/braaten-aili-without-you.html"},
{"url": "https://www.chordtela.com/2022/05/fire-amanda-minyak-goreng.html"},
{"url": "https://www.chordtela.com/2022/05/asbak-band-andai-saja.html"},
{"url": "https://www.chordtela.com/2022/05/pudjo-mardjoko-cukup-satene.html"},
{"url": "https://www.chordtela.com/2022/05/ed-sheeran-one-life.html"},
{"url": "https://www.chordtela.com/2022/05/david-iztambul-molah-banyanyi.html"},
{"url": "https://www.chordtela.com/2022/05/cut-rani-terlalu-sakit.html"},
{"url": "https://www.chordtela.com/2022/05/yulia-nadiva-sampai-bawah.html"},
{"url": "https://www.chordtela.com/2022/05/denis-farasya-ora-lilo.html"},
{"url": "https://www.chordtela.com/2022/05/anak-kompleks-ko-berubah.html"},
{"url": "https://www.chordtela.com/2022/05/arief-cinta-dibalas-tuba.html"},
{"url": "https://www.chordtela.com/2022/05/faouzia-thick-and-thin.html"},
{"url": "https://www.chordtela.com/2022/05/fabio-asher-rumah-singgah.html"},
{"url": "https://www.chordtela.com/2022/05/asbak-band-cinta-sendiri.html"},
{"url": "https://www.chordtela.com/2022/05/khalis-salah-menaruh-cinta.html"},
{"url": "https://www.chordtela.com/2022/05/safira-inema-biarlah-sepi.html"},
{"url": "https://www.chordtela.com/2022/05/hayati-shay-kamu-dimana.html"},
{"url": "https://www.chordtela.com/2022/05/rika-zella-baru-kusadari.html"},
{"url": "https://www.chordtela.com/2022/05/vita-alvia-cinta-pertama.html"},
{"url": "https://www.chordtela.com/2022/05/anak-kompleks-sapa-ganggu.html"},
{"url": "https://www.chordtela.com/2022/05/ovhi-firsty-dimabuak-cinto.html"},
{"url": "https://www.chordtela.com/2022/05/nanda-feraro-kaku-atine.html"},
{"url": "https://www.chordtela.com/2022/05/becky-g-guaynaa-tajin.html"},
{"url": "https://www.chordtela.com/2022/05/nirwana-trio-cinta-pertama.html"},
{"url": "https://www.chordtela.com/2022/05/selfi-yamma-uperrengi-kubertahan.html"},
{"url": "https://www.chordtela.com/2022/05/sasha-alex-sloan-adult.html"},
{"url": "https://www.chordtela.com/2022/05/mala-agatha-terlanjur-sayang.html"},
{"url": "https://www.chordtela.com/2022/05/rheka-restu-kecurangan-cinta.html"},
{"url": "https://www.chordtela.com/2022/05/alwalid-mz-kasih-suci.html"},
{"url": "https://www.chordtela.com/2022/05/luko-dihati-eda-ezrin.html"},
{"url": "https://www.chordtela.com/2022/05/near-pergi-ft-jay.html"},
{"url": "https://www.chordtela.com/2022/05/kang-wo-terminal-patria.html"},
{"url": "https://www.chordtela.com/2022/05/els-warouw-di-belakangku.html"},
{"url": "https://www.chordtela.com/2022/05/david-iztambul-jurang-dalam.html"},
{"url": "https://www.chordtela.com/2022/05/boywithuke-she-said-no.html"},
{"url": "https://www.chordtela.com/2022/05/febian-cinta-tak-bernyali.html"},
{"url": "https://www.chordtela.com/2022/05/papinka-kau-mencintai-sahabatku.html"},
{"url": "https://www.chordtela.com/2022/05/tiar-hutabarat-marsahit-lungun.html"},
{"url": "https://www.chordtela.com/2022/05/papinka-betapa-aku-mencintaimu.html"},
{"url": "https://www.chordtela.com/2022/05/widari-elen-salah-tresno.html"},
{"url": "https://www.chordtela.com/2022/05/meme-amelia-mupus-roso.html"},
{"url": "https://www.chordtela.com/2022/05/okta-isty-nikah-siri.html"},
{"url": "https://www.chordtela.com/2022/05/em-beihold-too-precious.html"},
{"url": "https://www.chordtela.com/2022/05/near-terlambat-echa-litong.html"},
{"url": "https://www.chordtela.com/2022/05/yelse-diantara-dua-pilihan.html"},
{"url": "https://www.chordtela.com/2022/05/putri-bulan-tresna-pedidi.html"},
{"url": "https://www.chordtela.com/2022/05/deddy-dores-surat-undangan.html"},
{"url": "https://www.chordtela.com/2022/05/gilang-agung-prapatan-tugu.html"},
{"url": "https://www.chordtela.com/2022/05/mkartikawati-andai-masih-bisa.html"},
{"url": "https://www.chordtela.com/2022/05/happy-magdalena-sampai-disini.html"},
{"url": "https://www.chordtela.com/2022/05/calvin-kp-takut-sayang.html"},
{"url": "https://www.chordtela.com/2022/05/bingrvb-melihat-dengan-hati.html"},
{"url": "https://www.chordtela.com/2022/05/silva-hayati-jangan-buruk-sangka.html"},
{"url": "https://www.chordtela.com/2022/05/carrie-underwood-she-dont-know.html"},
{"url": "https://www.chordtela.com/2022/05/netta-i-love-my-nails.html"},
{"url": "https://www.chordtela.com/2022/05/sri-fayola-mampagadang-jajak-luko.html"},
{"url": "https://www.chordtela.com/2022/05/deddy-dores-kemana-kan-kucari.html"},
{"url": "https://www.chordtela.com/2022/05/della-firdatia-sibuk-dengan-duniamu.html"},
{"url": "https://www.chordtela.com/2022/05/ifandra-alah-kanasib-sidagang-malang.html"},
{"url": "https://www.chordtela.com/2022/05/anak-kompleks-jang-datang-kembali.html"},
{"url": "https://www.chordtela.com/2022/05/latansana-band-dalam-sujud-cinta.html"},
{"url": "https://www.chordtela.com/2022/05/thomas-arya-rindu-yang-mengusik.html"},
{"url": "https://www.chordtela.com/2022/05/najwa-aia-mato-kajawek-tanyo.html"},
{"url": "https://www.chordtela.com/2022/05/fresly-nikijuluw-rasa-su-kalah.html"},
{"url": "https://www.chordtela.com/2022/05/fitri-vivita-kamu-yang-ganteng.html"},
{"url": "https://www.chordtela.com/2022/05/labrak-squad-sahabat-jadi-keluarga.html"},
{"url": "https://www.chordtela.com/2022/05/ichad-bless-masih-yang-terbaik.html"},
{"url": "https://www.chordtela.com/2022/05/rheka-restu-luka-tak-berdarah.html"},
{"url": "https://www.chordtela.com/2022/05/zack-tabudlo-as-you-are.html"},
{"url": "https://www.chordtela.com/2022/05/chase-matthew-everything-he-couldnt.html"},
{"url": "https://www.chordtela.com/2022/05/angga-eqino-laksana-ranting-kering.html"},
{"url": "https://www.chordtela.com/2022/05/basados-trio-jora-ma-au.html"},
{"url": "https://www.chordtela.com/2022/05/thomas-arya-bukan-tak-setia.html"},
{"url": "https://www.chordtela.com/2022/05/defri-juliant-biarkan-semua-berlalu.html"},
{"url": "https://www.chordtela.com/2022/05/alep-santosa-sing-dadi-belanjaang.html"},
{"url": "https://www.chordtela.com/2022/05/thomas-arya-cinta-bersimpuh-abadi.html"},
{"url": "https://www.chordtela.com/2022/05/thomas-arya-aku-yang-terluka.html"},
{"url": "https://www.chordtela.com/2022/05/vanny-vabiola-alasan-kau-tinggalkan.html"},
{"url": "https://www.chordtela.com/2022/05/sasya-arkhisna-full-senyum-sayang.html"},
{"url": "https://www.chordtela.com/2022/05/sri-fayola-sayang-tiado-artinyo.html"},
{"url": "https://www.chordtela.com/2022/05/haico-aku-lepas-kamu-cinta.html"},
{"url": "https://www.chordtela.com/2022/05/eki-volad-kacang-lupa-kulitnya.html"},
{"url": "https://www.chordtela.com/2022/05/flume-feat-emma-louise-hollow.html"},
{"url": "https://www.chordtela.com/2022/05/rambun-pamenan-cinto-saputiah-mego.html"},
{"url": "https://www.chordtela.com/2022/05/hendrik-pangestu-ninggal-cerito-loro.html"},
{"url": "https://www.chordtela.com/2022/05/%E2%80%8Bmxmtoon-learn-to-love-you.html"},
{"url": "https://www.chordtela.com/2022/05/gryffin-alive-with-calle-lehmann.html"},
{"url": "https://www.chordtela.com/2022/05/samuel-cipta-aku-kamu-semesta.html"},
{"url": "https://www.chordtela.com/2022/05/century-trio-memory-tao-toba.html"},
{"url": "https://www.chordtela.com/2022/05/sazqia-rayani-acok-di-patangih.html"},
{"url": "https://www.chordtela.com/2022/05/dj-qhelfin-air-mata-jatuh.html"},
{"url": "https://www.chordtela.com/2022/05/tootsielicious-dont-touch-my-crown.html"},
{"url": "https://www.chordtela.com/2022/05/rika-zella-cinta-yang-kembali.html"},
{"url": "https://www.chordtela.com/2022/05/near-satu-bintang-ft-jay.html"},
{"url": "https://www.chordtela.com/2022/05/novi-a-munadi-cinta-sendiri.html"},
{"url": "https://www.chordtela.com/2022/05/near-pergi-sudah-ape-napsor.html"},
{"url": "https://www.chordtela.com/2022/05/gustrian-geno-dek-ulah-pitih.html"},
{"url": "https://www.chordtela.com/2022/05/daniel-maestro-cando-karambia-condong.html"},
{"url": "https://www.chordtela.com/2022/05/lord-huron-your-other-life.html"},
{"url": "https://www.chordtela.com/2022/05/brett-eldredge-i-feel-fine.html"},
{"url": "https://www.chordtela.com/2022/05/laura-nick-manullang-tarsunggul-au.html"},
{"url": "https://www.chordtela.com/2022/05/david-iztambul-cinto-balain-raso.html"},
{"url": "https://www.chordtela.com/2022/05/pakdhe-baz-opo-iseh-ono.html"},
{"url": "https://www.chordtela.com/2022/05/novi-rizki-pikir-pikir-dulu.html"},
{"url": "https://www.chordtela.com/2022/05/keisya-levronka-tak-ingin-usai.html"},
{"url": "https://www.chordtela.com/2022/05/near-sampai-akhir-usia-jay.html"},
{"url": "https://www.chordtela.com/2022/05/yollans-cotto-manangih-untuak-uda.html"},
{"url": "https://www.chordtela.com/2022/05/jamal-suliwa-taseso-hiduik-dikampuang.html"},
{"url": "https://www.chordtela.com/2022/05/paolo-lee-tuhan-jaga-dia.html"},
{"url": "https://www.chordtela.com/2022/05/deddy-dores-aku-cinta-padamu.html"},
{"url": "https://www.chordtela.com/2022/05/ed-sheeran-i-will-remember-you.html"},
{"url": "https://www.chordtela.com/2022/05/puspa-indah-ft-aprilian-manjakan-aku.html"},
{"url": "https://www.chordtela.com/2022/05/arcade-fire-unconditional-i-lookout-kid.html"},
{"url": "https://www.chordtela.com/2022/05/mxmtoon-dance-end-of-the-world.html"},
{"url": "https://www.chordtela.com/2022/05/niken-salindry-kelingan-sing-tak-sayang.html"},
{"url": "https://www.chordtela.com/2022/05/arjuna-89-mengapa-kau-meninggalkan-ku.html"},
{"url": "https://www.chordtela.com/2022/05/andika-mahesa-kangen-band-sampai-disini.html"},
{"url": "https://www.chordtela.com/2022/05/stephen-sanchez-until-i-found-you.html"},
{"url": "https://www.chordtela.com/2022/05/rosie-mcclelland-safe-in-your-love.html"},
{"url": "https://www.chordtela.com/2022/05/dato-seri-vida-muah-muah-raya.html"},
{"url": "https://www.chordtela.com/2022/05/anneth-sampai-kapan-jaga-hati-untukmu.html"},
{"url": "https://www.chordtela.com/2022/05/now-united-heartbreak-on-the-dancefloor.html"},
{"url": "https://www.chordtela.com/2022/05/ziell-ferdian-ada-hati-yang-dijaga.html"},
{"url": "https://www.chordtela.com/2022/05/ed-sheeran-welcome-to-the-world.html"},
{"url": "https://www.chordtela.com/2022/05/andika-mahesa-kangen-band-tentang-cinta.html"},
{"url": "https://www.chordtela.com/2022/05/aprilian-ft-tryana-sulit-ku-miliki.html"},
{"url": "https://www.chordtela.com/2022/05/febian-feat-yollanda-masih-menyimpan-cinta.html"},
{"url": "https://www.chordtela.com/2022/05/k-391-victor-crone-lonely-world.html"},
{"url": "https://www.chordtela.com/2022/05/renggi-thailand-ku-titip-cinta-ini.html"},
{"url": "https://www.chordtela.com/2022/05/betrand-peto-putra-onsu-setengah-hati.html"},
{"url": "https://www.chordtela.com/2022/05/near-andai-engg-x-iz-one.html"},
{"url": "https://www.chordtela.com/2022/05/fany-zee-jangan-buat-aku-menangis.html"},
{"url": "https://www.chordtela.com/2022/05/justy-aldrin-ade-nona-feat-gerald.html"},
{"url": "https://www.chordtela.com/2022/05/silva-hayati-urang-lalok-ayah-batanggang.html"},
{"url": "https://www.chordtela.com/2022/05/lyn-lapid-messed-up-on-christmas.html"},
{"url": "https://www.chordtela.com/2022/05/vanny-vabiola-aku-tak-mau-lagi.html"},
{"url": "https://www.chordtela.com/2022/05/andika-mahesa-ft-balqis-tak-rela.html"},
{"url": "https://www.chordtela.com/2022/05/becky-g-baile-con-mi-ex.html"},
{"url": "https://www.chordtela.com/2022/05/gihon-marel-eno-smaper-anyo-hanyut.html"},
{"url": "https://www.chordtela.com/2022/05/kangen-band-terima-kasih-patah-hati.html"},
{"url": "https://www.chordtela.com/2022/05/anggrek-ft-dabee-tak-mungkin-berharap.html"},
{"url": "https://www.chordtela.com/2022/05/hobby-kerauhan-ary-kencana-feat-marco.html"},
{"url": "https://www.chordtela.com/2022/05/novi-a-munadi-dunia-bukan-ilusi.html"},
{"url": "https://www.chordtela.com/2022/05/imam-ft-yollanda-terpisah-karena-harta.html"},
{"url": "https://www.chordtela.com/2022/05/gak-lemos-cak-ukil-dika-mbeluk.html"},
{"url": "https://www.chordtela.com/2022/05/anggi-chandra-bialah-batu-den-tanak.html"},
{"url": "https://www.chordtela.com/2022/05/rani-chania-jan-panek-panek-bana.html"},
{"url": "https://www.chordtela.com/2022/05/vicky-marchel-ku-kecewa-kau-bahagia.html"},
{"url": "https://www.chordtela.com/2022/05/nanda-feraro-kembang-waru-dadi-awu.html"},
{"url": "https://www.chordtela.com/2022/05/deddy-dores-menanti-dibawah-pohon-kamboja.html"},
{"url": "https://www.chordtela.com/2022/05/sinatra-alif-bila-memang-harus-pergi.html"},
{"url": "https://www.chordtela.com/2022/05/ella-mai-a-mess-feat-lucky-daye.html"},
{"url": "https://www.chordtela.com/2022/05/esok-kan-bahagia-agiel-ft-rika-masya.html"},
{"url": "https://www.chordtela.com/2022/05/savannah-dexter-x-brabo-gator-low-down.html"},
{"url": "https://www.chordtela.com/2022/05/endank-soekamti-x-ndarboy-genk-wayahe-hiling.html"},
{"url": "https://www.chordtela.com/2022/05/roza-selvia-ft-ifandra-satitiak-jadikan-lauik.html"},
{"url": "https://www.chordtela.com/2022/05/pacar-rahasia-ttm-akustik-ft-putri-andien.html"},
{"url": "https://www.chordtela.com/2022/05/andika-mahesa-kangen-band-jika-mengerti-aku.html"},
{"url": "https://www.chordtela.com/2022/05/david-iztambul-tatutuik-jaso-dek-bansaik-diri.html"},
{"url": "https://www.chordtela.com/2022/05/the-boys-trio-memory-tao-toba-2.html"},
{"url": "https://www.chordtela.com/2022/05/ramlan-yahya-feat-cut-rani-tiada-mungkin.html"},
{"url": "https://www.chordtela.com/2022/05/evi-masamba-kukejar-kau-ke-ujung-dunia.html"},
{"url": "https://www.chordtela.com/2022/05/one-voice-childrens-choir-no-plan-b.html"},
{"url": "https://www.chordtela.com/2022/05/fearless-soul-dont-you-dare-give-up.html"},
{"url": "https://www.chordtela.com/2022/05/satru-3-kok-gething-aku-sasya-arkhisna.html"},
{"url": "https://www.chordtela.com/2022/05/anak-kompleks-tempat-curhat-ft-eda-naziela.html"},
{"url": "https://www.chordtela.com/2022/05/near-pendam-rosary-unha-x-iz-one.html"},
{"url": "https://www.chordtela.com/2022/05/wizz-baker-feat-ecko-show-bahagia-pergi.html"},
{"url": "https://www.chordtela.com/2022/05/aprilian-feat-rheka-restu-hidup-dalam-mimpi.html"},
{"url": "https://www.chordtela.com/2022/05/varenina-ft-nando-satoko-balabiah-dek-piutang.html"},
{"url": "https://www.chordtela.com/2022/05/arief-ft-fauzana-cinta-mu-rindu-ku.html"},
{"url": "https://www.chordtela.com/2022/05/no-name-crew-maitua-ft-remobar-crew.html"},
{"url": "https://www.chordtela.com/2022/05/5-seconds-of-summer-me-myself-i.html"},
{"url": "https://www.chordtela.com/2022/05/jangan-kau-pergi-bennito-feat-yusi-yusran.html"},
{"url": "https://www.chordtela.com/2022/05/nguyahi-segoro-adistya-mayasari-feat-eko-bece.html"},
{"url": "https://www.chordtela.com/2022/05/kangen-swarane-sasya-arkhisna-ft-ageng-music.html"},
{"url": "https://www.chordtela.com/2022/05/windra-ft-vadilla-sukma-palaminan-nan-dinantikan.html"},
{"url": "https://www.chordtela.com/2022/05/yuni-sae-lah-jaleh-luko-baasami-juo.html"},
{"url": "https://www.chordtela.com/2022/05/ratu-sikumbang-ibo-ibo-hati-den-mandeh.html"},
{"url": "https://www.chordtela.com/2022/05/andika-mahesa-x-putra-siregar-terhukum-rindu.html"}
]
